LICENSE
wkt_poly_to_image/__init__.py
wkt_poly_to_image/convert.py
wkt_poly_to_image-0.1.1.dist-info/entry_points.txt
wkt_poly_to_image-0.1.1.dist-info/LICENSE
wkt_poly_to_image-0.1.1.dist-info/WHEEL
wkt_poly_to_image-0.1.1.dist-info/METADATA
wkt_poly_to_image-0.1.1.dist-info/RECORD
