Metadata-Version: 2.1
Name: wkt-poly-to-image
Version: 0.1.1
Summary: A python library to convert wkt polygons into raster images.
Home-page: https://gitlab.com/bronsonbdevost/wkt_poly_to_image
License: MIT
Keywords: shapely,raster,convert
Author: Bronson Brown-deVost
Author-email: bronsonbdevost@gmail.com
Requires-Python: >=3.7,<3.11
Classifier: License :: OSI Approved :: MIT License
Classifier: Programming Language :: Python :: 3
Classifier: Programming Language :: Python :: 3.7
Classifier: Programming Language :: Python :: 3.8
Classifier: Programming Language :: Python :: 3.9
Requires-Dist: Shapely (>=1.7.1,<2.0.0)
Requires-Dist: numpy (>=1.21.2,<2.0.0)
Requires-Dist: rasterio (>=1.2.8,<2.0.0)
Project-URL: Repository, https://gitlab.com/bronsonbdevost/wkt_poly_to_image
